QWeaver/__Init__.py
QWeaver/example.py
QWeaver-0.0.1.dist-info/LICENSE
QWeaver-0.0.1.dist-info/METADATA
QWeaver-0.0.1.dist-info/WHEEL
QWeaver-0.0.1.dist-info/top_level.txt
QWeaver-0.0.1.dist-info/RECORD
