Metadata-Version: 2.1
Name: QWeaver
Version: 0.0.1
Summary: Quantum Majorana Fermion Braiding Library
Home-page: https://github.com/TriSarahTop/QWeaver
Author: Sarah Ram
Author-email: ignislumiere@gmail.com
License: UNKNOWN
Project-URL: Bug Tracker, https://github.com/TriSarahTop/QWeaver/issues
Platform: UNKNOWN
Classifier: Programming Language :: Python :: 3
Classifier: License :: OSI Approved :: MIT License
Classifier: Operating System :: OS Independent
Requires-Python: >=3.6
License-File: LICENSE
